<?xml version="1.0" encoding="UTF-8" standalone="yes"?>
<dataset>
    <record>
        <EFFECTIVE_DATE>20231022</EFFECTIVE_DATE>
        <MEMBER_ID>70010010101</MEMBER_ID>
        <LO_RANGE>2200012800000000000</LO_RANGE>
        <HI_RANGE>2200012899999999999</HI_RANGE>
        <BANK_NAME>Gazprombank</BANK_NAME>
        <PRODUCT_CODE>PRD</PRODUCT_CODE>
        <COUNTRY_CODE>643</COUNTRY_CODE>
        <BILCURRENCY_CODE>643</BILCURRENCY_CODE>
    </record>
    <record>
        <EFFECTIVE_DATE>20231022</EFFECTIVE_DATE>
        <MEMBER_ID>70100020101</MEMBER_ID>
        <LO_RANGE>2200020100000000000</LO_RANGE>
        <HI_RANGE>2200020109999999999</HI_RANGE>
        <BANK_NAME>RNCB</BANK_NAME>
        <PRODUCT_CODE>MDT</PRODUCT_CODE>
        <COUNTRY_CODE>643</COUNTRY_CODE>
        <BILCURRENCY_CODE>643</BILCURRENCY_CODE>
    </record>
    <record>
        <EFFECTIVE_DATE>20231022</EFFECTIVE_DATE>
        <MEMBER_ID>70100020101</MEMBER_ID>
        <LO_RANGE>2200020200000000000</LO_RANGE>
        <HI_RANGE>2200020204999999999</HI_RANGE>
        <BANK_NAME>RNCB</BANK_NAME>
        <PRODUCT_CODE>CCD</PRODUCT_CODE>
        <COUNTRY_CODE>643</COUNTRY_CODE>
        <BILCURRENCY_CODE>643</BILCURRENCY_CODE>
    </record>
    <record>
        <EFFECTIVE_DATE>20231022</EFFECTIVE_DATE>
        <MEMBER_ID>70100020101</MEMBER_ID>
        <LO_RANGE>2200020206000000000</LO_RANGE>
        <HI_RANGE>2200020279999999999</HI_RANGE>
        <BANK_NAME>RNCB</BANK_NAME>
        <PRODUCT_CODE>CCD</PRODUCT_CODE>
        <COUNTRY_CODE>643</COUNTRY_CODE>
        <BILCURRENCY_CODE>643</BILCURRENCY_CODE>
    </record>
    <record>
        <EFFECTIVE_DATE>20231022</EFFECTIVE_DATE>
        <MEMBER_ID>70100020101</MEMBER_ID>
        <LO_RANGE>2200020300000000000</LO_RANGE>
        <HI_RANGE>2200020300699999999</HI_RANGE>
        <BANK_NAME>RNCB</BANK_NAME>
        <PRODUCT_CODE>MCB</PRODUCT_CODE>
        <COUNTRY_CODE>643</COUNTRY_CODE>
        <BILCURRENCY_CODE>643</BILCURRENCY_CODE>
    </record>
    <record>
        <EFFECTIVE_DATE>20231022</EFFECTIVE_DATE>
        <MEMBER_ID>70100020101</MEMBER_ID>
        <LO_RANGE>2200020400000000000</LO_RANGE>
        <HI_RANGE>2200020400499999999</HI_RANGE>
        <BANK_NAME>RNCB</BANK_NAME>
        <PRODUCT_CODE>PRD</PRODUCT_CODE>
        <COUNTRY_CODE>643</COUNTRY_CODE>
        <BILCURRENCY_CODE>643</BILCURRENCY_CODE>
    </record>
    <record>
        <EFFECTIVE_DATE>20231022</EFFECTIVE_DATE>
        <MEMBER_ID>70100020101</MEMBER_ID>
        <LO_RANGE>2200020400500000000</LO_RANGE>
        <HI_RANGE>2200020401999999999</HI_RANGE>
        <BANK_NAME>RNCB</BANK_NAME>
        <PRODUCT_CODE>PRD</PRODUCT_CODE>
        <COUNTRY_CODE>643</COUNTRY_CODE>
        <BILCURRENCY_CODE>643</BILCURRENCY_CODE>
    </record>
    <record>
        <EFFECTIVE_DATE>20231022</EFFECTIVE_DATE>
        <MEMBER_ID>70100020101</MEMBER_ID>
        <LO_RANGE>2200020500000000000</LO_RANGE>
        <HI_RANGE>2200020500499999999</HI_RANGE>
        <BANK_NAME>RNCB</BANK_NAME>
        <PRODUCT_CODE>CPP</PRODUCT_CODE>
        <COUNTRY_CODE>643</COUNTRY_CODE>
        <BILCURRENCY_CODE>643</BILCURRENCY_CODE>
    </record>
    <record>
        <EFFECTIVE_DATE>20231022</EFFECTIVE_DATE>
        <MEMBER_ID>70100020101</MEMBER_ID>
        <LO_RANGE>2200020600000000000</LO_RANGE>
        <HI_RANGE>2200020606999999999</HI_RANGE>
        <BANK_NAME>RNCB</BANK_NAME>
        <PRODUCT_CODE>CCD</PRODUCT_CODE>
        <COUNTRY_CODE>643</COUNTRY_CODE>
        <BILCURRENCY_CODE>643</BILCURRENCY_CODE>
    </record>
    <record>
        <EFFECTIVE_DATE>20231022</EFFECTIVE_DATE>
        <MEMBER_ID>70100020101</MEMBER_ID>
        <LO_RANGE>2200020700000000000</LO_RANGE>
        <HI_RANGE>2200020739999999999</HI_RANGE>
        <BANK_NAME>RNCB</BANK_NAME>
        <PRODUCT_CODE>CCD</PRODUCT_CODE>
        <COUNTRY_CODE>643</COUNTRY_CODE>
        <BILCURRENCY_CODE>643</BILCURRENCY_CODE>
    </record>
    <record>
        <EFFECTIVE_DATE>20231022</EFFECTIVE_DATE>
        <MEMBER_ID>70100020101</MEMBER_ID>
        <LO_RANGE>2200020800000000000</LO_RANGE>
        <HI_RANGE>2200020809999999999</HI_RANGE>
        <BANK_NAME>RNCB</BANK_NAME>
        <PRODUCT_CODE>MDT</PRODUCT_CODE>
        <COUNTRY_CODE>643</COUNTRY_CODE>
        <BILCURRENCY_CODE>643</BILCURRENCY_CODE>
    </record>
    <record>
        <EFFECTIVE_DATE>20231022</EFFECTIVE_DATE>
        <MEMBER_ID>70100020101</MEMBER_ID>
        <LO_RANGE>2200020900000000000</LO_RANGE>
        <HI_RANGE>2200020909999999999</HI_RANGE>
        <BANK_NAME>RNCB</BANK_NAME>
        <PRODUCT_CODE>CCD</PRODUCT_CODE>
        <COUNTRY_CODE>643</COUNTRY_CODE>
        <BILCURRENCY_CODE>643</BILCURRENCY_CODE>
    </record>
    <record>
        <EFFECTIVE_DATE>20231022</EFFECTIVE_DATE>
        <MEMBER_ID>70100020101</MEMBER_ID>
        <LO_RANGE>2200020910000000000</LO_RANGE>
        <HI_RANGE>2200020937999999999</HI_RANGE>
        <BANK_NAME>RNCB</BANK_NAME>
        <PRODUCT_CODE>CCD</PRODUCT_CODE>
        <COUNTRY_CODE>643</COUNTRY_CODE>
        <BILCURRENCY_CODE>643</BILCURRENCY_CODE>
    </record>
    <record>
        <EFFECTIVE_DATE>20231022</EFFECTIVE_DATE>
        <MEMBER_ID>70100020101</MEMBER_ID>
        <LO_RANGE>2200021000000000000</LO_RANGE>
        <HI_RANGE>2200021099999999999</HI_RANGE>
        <BANK_NAME>RNCB</BANK_NAME>
        <PRODUCT_CODE>MDT</PRODUCT_CODE>
        <COUNTRY_CODE>643</COUNTRY_CODE>
        <BILCURRENCY_CODE>643</BILCURRENCY_CODE>
    </record>
    <record>
        <EFFECTIVE_DATE>20231022</EFFECTIVE_DATE>
        <MEMBER_ID>70100020101</MEMBER_ID>
        <LO_RANGE>2200021100000000000</LO_RANGE>
        <HI_RANGE>2200021104999999999</HI_RANGE>
        <BANK_NAME>RNCB</BANK_NAME>
        <PRODUCT_CODE>PPB</PRODUCT_CODE>
        <COUNTRY_CODE>643</COUNTRY_CODE>
        <BILCURRENCY_CODE>643</BILCURRENCY_CODE>
    </record>
    <record>
        <EFFECTIVE_DATE>20231022</EFFECTIVE_DATE>
        <MEMBER_ID>70100020101</MEMBER_ID>
        <LO_RANGE>2200021200000000000</LO_RANGE>
        <HI_RANGE>2200021204999999999</HI_RANGE>
        <BANK_NAME>RNCB</BANK_NAME>
        <PRODUCT_CODE>PPB</PRODUCT_CODE>
        <COUNTRY_CODE>643</COUNTRY_CODE>
        <BILCURRENCY_CODE>643</BILCURRENCY_CODE>
    </record>
    <record>
        <EFFECTIVE_DATE>20231022</EFFECTIVE_DATE>
        <MEMBER_ID>70100020101</MEMBER_ID>
        <LO_RANGE>2200021300000000000</LO_RANGE>
        <HI_RANGE>2200021399999999999</HI_RANGE>
        <BANK_NAME>RNCB</BANK_NAME>
        <PRODUCT_CODE>TKN</PRODUCT_CODE>
        <COUNTRY_CODE>643</COUNTRY_CODE>
        <BILCURRENCY_CODE>643</BILCURRENCY_CODE>
    </record>
    <record>
        <EFFECTIVE_DATE>20231022</EFFECTIVE_DATE>
        <MEMBER_ID>70220030101</MEMBER_ID>
        <LO_RANGE>2200030130000000000</LO_RANGE>
        <HI_RANGE>2200030189999999999</HI_RANGE>
        <BANK_NAME>Promsvyazbank</BANK_NAME>
        <PRODUCT_CODE>CPP</PRODUCT_CODE>
        <COUNTRY_CODE>643</COUNTRY_CODE>
        <BILCURRENCY_CODE>643</BILCURRENCY_CODE>
    </record>
    <record>
        <EFFECTIVE_DATE>20231022</EFFECTIVE_DATE>
        <MEMBER_ID>70220030101</MEMBER_ID>
        <LO_RANGE>2200030210000000000</LO_RANGE>
        <HI_RANGE>2200030239999999999</HI_RANGE>
        <BANK_NAME>Promsvyazbank</BANK_NAME>
        <PRODUCT_CODE>PRD</PRODUCT_CODE>
        <COUNTRY_CODE>643</COUNTRY_CODE>
        <BILCURRENCY_CODE>643</BILCURRENCY_CODE>
    </record>
    <record>
        <EFFECTIVE_DATE>20231022</EFFECTIVE_DATE>
        <MEMBER_ID>70220030101</MEMBER_ID>
        <LO_RANGE>2200030310000000000</LO_RANGE>
        <HI_RANGE>2200030349999999999</HI_RANGE>
        <BANK_NAME>Promsvyazbank</BANK_NAME>
        <PRODUCT_CODE>PRD</PRODUCT_CODE>
        <COUNTRY_CODE>643</COUNTRY_CODE>
        <BILCURRENCY_CODE>643</BILCURRENCY_CODE>
    </record>
    <record>
        <EFFECTIVE_DATE>20231022</EFFECTIVE_DATE>
        <MEMBER_ID>70220030101</MEMBER_ID>
        <LO_RANGE>2200030350000000000</LO_RANGE>
        <HI_RANGE>2200030359999999999</HI_RANGE>
        <BANK_NAME>Promsvyazbank</BANK_NAME>
        <PRODUCT_CODE>PRD</PRODUCT_CODE>
        <COUNTRY_CODE>643</COUNTRY_CODE>
        <BILCURRENCY_CODE>643</BILCURRENCY_CODE>
    </record>
    <record>
        <EFFECTIVE_DATE>20231022</EFFECTIVE_DATE>
        <MEMBER_ID>70220030101</MEMBER_ID>
        <LO_RANGE>2200030401000000000</LO_RANGE>
        <HI_RANGE>2200030455999999999</HI_RANGE>
        <BANK_NAME>Promsvyazbank</BANK_NAME>
        <PRODUCT_CODE>PPB</PRODUCT_CODE>
        <COUNTRY_CODE>643</COUNTRY_CODE>
        <BILCURRENCY_CODE>643</BILCURRENCY_CODE>
    </record>
    <record>
        <EFFECTIVE_DATE>20231022</EFFECTIVE_DATE>
        <MEMBER_ID>70220030101</MEMBER_ID>
        <LO_RANGE>2200030501000000000</LO_RANGE>
        <HI_RANGE>2200030559999999999</HI_RANGE>
        <BANK_NAME>Promsvyazbank</BANK_NAME>
        <PRODUCT_CODE>PRD</PRODUCT_CODE>
        <COUNTRY_CODE>643</COUNTRY_CODE>
        <BILCURRENCY_CODE>643</BILCURRENCY_CODE>
    </record>
    <record>
        <EFFECTIVE_DATE>20231022</EFFECTIVE_DATE>
        <MEMBER_ID>70220030101</MEMBER_ID>
        <LO_RANGE>2200030601000000000</LO_RANGE>
        <HI_RANGE>2200030639999999999</HI_RANGE>
        <BANK_NAME>Promsvyazbank</BANK_NAME>
        <PRODUCT_CODE>CPP</PRODUCT_CODE>
        <COUNTRY_CODE>643</COUNTRY_CODE>
        <BILCURRENCY_CODE>643</BILCURRENCY_CODE>
    </record>
    <record>
        <EFFECTIVE_DATE>20231022</EFFECTIVE_DATE>
        <MEMBER_ID>70220030101</MEMBER_ID>
        <LO_RANGE>2200030670000000000</LO_RANGE>
        <HI_RANGE>2200030699999999999</HI_RANGE>
        <BANK_NAME>Promsvyazbank</BANK_NAME>
        <PRODUCT_CODE>CPP</PRODUCT_CODE>
        <COUNTRY_CODE>643</COUNTRY_CODE>
        <BILCURRENCY_CODE>643</BILCURRENCY_CODE>
    </record>
    <record>
        <EFFECTIVE_DATE>20231022</EFFECTIVE_DATE>
        <MEMBER_ID>70220030101</MEMBER_ID>
        <LO_RANGE>2200030701000000000</LO_RANGE>
        <HI_RANGE>2200030707999999999</HI_RANGE>
        <BANK_NAME>Promsvyazbank</BANK_NAME>
        <PRODUCT_CODE>NPB</PRODUCT_CODE>
        <COUNTRY_CODE>643</COUNTRY_CODE>
        <BILCURRENCY_CODE>643</BILCURRENCY_CODE>
    </record>
    <record>
        <EFFECTIVE_DATE>20231022</EFFECTIVE_DATE>
        <MEMBER_ID>70220030101</MEMBER_ID>
        <LO_RANGE>2200030800000000000</LO_RANGE>
        <HI_RANGE>2200030899999999999</HI_RANGE>
        <BANK_NAME>Promsvyazbank</BANK_NAME>
        <PRODUCT_CODE>TKN</PRODUCT_CODE>
        <COUNTRY_CODE>643</COUNTRY_CODE>
        <BILCURRENCY_CODE>643</BILCURRENCY_CODE>
    </record>
    <record>
        <EFFECTIVE_DATE>20231022</EFFECTIVE_DATE>
        <MEMBER_ID>70220030101</MEMBER_ID>
        <LO_RANGE>2200030901000000000</LO_RANGE>
        <HI_RANGE>2200030919999999999</HI_RANGE>
        <BANK_NAME>Promsvyazbank</BANK_NAME>
        <PRODUCT_CODE>PRD</PRODUCT_CODE>
        <COUNTRY_CODE>643</COUNTRY_CODE>
        <BILCURRENCY_CODE>643</BILCURRENCY_CODE>
    </record>
    <record>
        <EFFECTIVE_DATE>20231022</EFFECTIVE_DATE>
        <MEMBER_ID>70220030101</MEMBER_ID>
        <LO_RANGE>2200031000000000000</LO_RANGE>
        <HI_RANGE>2200031099999999999</HI_RANGE>
        <BANK_NAME>Promsvyazbank</BANK_NAME>
        <PRODUCT_CODE>TKN</PRODUCT_CODE>
        <COUNTRY_CODE>643</COUNTRY_CODE>
        <BILCURRENCY_CODE>643</BILCURRENCY_CODE>
    </record>
    <record>
        <EFFECTIVE_DATE>20231022</EFFECTIVE_DATE>
        <MEMBER_ID>70220030101</MEMBER_ID>
        <LO_RANGE>2200031101000000000</LO_RANGE>
        <HI_RANGE>2200031119999999999</HI_RANGE>
        <BANK_NAME>Promsvyazbank</BANK_NAME>
        <PRODUCT_CODE>MSA</PRODUCT_CODE>
        <COUNTRY_CODE>643</COUNTRY_CODE>
        <BILCURRENCY_CODE>643</BILCURRENCY_CODE>
    </record>
    <record>
        <EFFECTIVE_DATE>20231022</EFFECTIVE_DATE>
        <MEMBER_ID>70220030101</MEMBER_ID>
        <LO_RANGE>2200031130000000000</LO_RANGE>
        <HI_RANGE>2200031169999999999</HI_RANGE>
        <BANK_NAME>Promsvyazbank</BANK_NAME>
        <PRODUCT_CODE>MSA</PRODUCT_CODE>
        <COUNTRY_CODE>643</COUNTRY_CODE>
        <BILCURRENCY_CODE>643</BILCURRENCY_CODE>
    </record>
    <record>
        <EFFECTIVE_DATE>20231022</EFFECTIVE_DATE>
        <MEMBER_ID>70220030101</MEMBER_ID>
        <LO_RANGE>2200031200000000000</LO_RANGE>
        <HI_RANGE>2200031299999999999</HI_RANGE>
        <BANK_NAME>Promsvyazbank</BANK_NAME>
        <PRODUCT_CODE>TKN</PRODUCT_CODE>
        <COUNTRY_CODE>643</COUNTRY_CODE>
        <BILCURRENCY_CODE>643</BILCURRENCY_CODE>
    </record>
    <record>
        <EFFECTIVE_DATE>20231022</EFFECTIVE_DATE>
        <MEMBER_ID>70220030101</MEMBER_ID>
        <LO_RANGE>2200031301000000000</LO_RANGE>
        <HI_RANGE>2200031319999999999</HI_RANGE>
        <BANK_NAME>Promsvyazbank</BANK_NAME>
        <PRODUCT_CODE>MSA</PRODUCT_CODE>
        <COUNTRY_CODE>643</COUNTRY_CODE>
        <BILCURRENCY_CODE>643</BILCURRENCY_CODE>
    </record>
    <record>
        <EFFECTIVE_DATE>20231022</EFFECTIVE_DATE>
        <MEMBER_ID>70220030101</MEMBER_ID>
        <LO_RANGE>2200031401000000000</LO_RANGE>
        <HI_RANGE>2200031405999999999</HI_RANGE>
        <BANK_NAME>Promsvyazbank</BANK_NAME>
        <PRODUCT_CODE>MSB</PRODUCT_CODE>
        <COUNTRY_CODE>643</COUNTRY_CODE>
        <BILCURRENCY_CODE>643</BILCURRENCY_CODE>
    </record>
    <record>
        <EFFECTIVE_DATE>20231022</EFFECTIVE_DATE>
        <MEMBER_ID>70220030101</MEMBER_ID>
        <LO_RANGE>2200031417000000000</LO_RANGE>
        <HI_RANGE>2200031419999999999</HI_RANGE>
        <BANK_NAME>Promsvyazbank</BANK_NAME>
        <PRODUCT_CODE>MSB</PRODUCT_CODE>
        <COUNTRY_CODE>643</COUNTRY_CODE>
        <BILCURRENCY_CODE>643</BILCURRENCY_CODE>
    </record>
    <record>
        <EFFECTIVE_DATE>20231022</EFFECTIVE_DATE>
        <MEMBER_ID>70220030101</MEMBER_ID>
        <LO_RANGE>2200031600000000000</LO_RANGE>
        <HI_RANGE>2200031699999999999</HI_RANGE>
        <BANK_NAME>Promsvyazbank</BANK_NAME>
        <PRODUCT_CODE>TKN</PRODUCT_CODE>
        <COUNTRY_CODE>643</COUNTRY_CODE>
        <BILCURRENCY_CODE>643</BILCURRENCY_CODE>
    </record>
    <record>
        <EFFECTIVE_DATE>20231022</EFFECTIVE_DATE>
        <MEMBER_ID>70220030101</MEMBER_ID>
        <LO_RANGE>2200031800000000000</LO_RANGE>
        <HI_RANGE>2200031899999999999</HI_RANGE>
        <BANK_NAME>Promsvyazbank</BANK_NAME>
        <PRODUCT_CODE>TKN</PRODUCT_CODE>
        <COUNTRY_CODE>643</COUNTRY_CODE>
        <BILCURRENCY_CODE>643</BILCURRENCY_CODE>
    </record>
    <record>
        <EFFECTIVE_DATE>20231022</EFFECTIVE_DATE>
        <MEMBER_ID>70220030101</MEMBER_ID>
        <LO_RANGE>2200032000000000000</LO_RANGE>
        <HI_RANGE>2200032099999999999</HI_RANGE>
        <BANK_NAME>Promsvyazbank</BANK_NAME>
        <PRODUCT_CODE>TKN</PRODUCT_CODE>
        <COUNTRY_CODE>643</COUNTRY_CODE>
        <BILCURRENCY_CODE>643</BILCURRENCY_CODE>
    </record>
    <record>
        <EFFECTIVE_DATE>20231022</EFFECTIVE_DATE>
        <MEMBER_ID>70230040101</MEMBER_ID>
        <LO_RANGE>2200040100000000000</LO_RANGE>
        <HI_RANGE>2200040149999999999</HI_RANGE>
        <BANK_NAME>Russian Standard</BANK_NAME>
        <PRODUCT_CODE>PPP</PRODUCT_CODE>
        <COUNTRY_CODE>643</COUNTRY_CODE>
        <BILCURRENCY_CODE>643</BILCURRENCY_CODE>
    </record>
    <record>
        <EFFECTIVE_DATE>20231022</EFFECTIVE_DATE>
        <MEMBER_ID>70230040101</MEMBER_ID>
        <LO_RANGE>2200040150000000000</LO_RANGE>
        <HI_RANGE>2200040199999999999</HI_RANGE>
        <BANK_NAME>Russian Standard</BANK_NAME>
        <PRODUCT_CODE>PPP</PRODUCT_CODE>
        <COUNTRY_CODE>643</COUNTRY_CODE>
        <BILCURRENCY_CODE>643</BILCURRENCY_CODE>
    </record>
    <record>
        <EFFECTIVE_DATE>20231022</EFFECTIVE_DATE>
        <MEMBER_ID>70230040101</MEMBER_ID>
        <LO_RANGE>2200040200000000000</LO_RANGE>
        <HI_RANGE>2200040299999999999</HI_RANGE>
        <BANK_NAME>Russian Standard</BANK_NAME>
        <PRODUCT_CODE>CPP</PRODUCT_CODE>
        <COUNTRY_CODE>643</COUNTRY_CODE>
        <BILCURRENCY_CODE>643</BILCURRENCY_CODE>
    </record>
    <record>
        <EFFECTIVE_DATE>20231022</EFFECTIVE_DATE>
        <MEMBER_ID>70230040101</MEMBER_ID>
        <LO_RANGE>2200040300000000000</LO_RANGE>
        <HI_RANGE>2200040399999999999</HI_RANGE>
        <BANK_NAME>Russian Standard</BANK_NAME>
        <PRODUCT_CODE>PRD</PRODUCT_CODE>
        <COUNTRY_CODE>643</COUNTRY_CODE>
        <BILCURRENCY_CODE>643</BILCURRENCY_CODE>
    </record>
    <record>
        <EFFECTIVE_DATE>20231022</EFFECTIVE_DATE>
        <MEMBER_ID>70230040101</MEMBER_ID>
        <LO_RANGE>2200040400000000000</LO_RANGE>
        <HI_RANGE>2200040499999999999</HI_RANGE>
        <BANK_NAME>Russian Standard</BANK_NAME>
        <PRODUCT_CODE>TKN</PRODUCT_CODE>
        <COUNTRY_CODE>643</COUNTRY_CODE>
        <BILCURRENCY_CODE>643</BILCURRENCY_CODE>
    </record>
    <record>
        <EFFECTIVE_DATE>20231022</EFFECTIVE_DATE>
        <MEMBER_ID>70230040101</MEMBER_ID>
        <LO_RANGE>2200040500000000000</LO_RANGE>
        <HI_RANGE>2200040599999999999</HI_RANGE>
        <BANK_NAME>Russian Standard</BANK_NAME>
        <PRODUCT_CODE>MSA</PRODUCT_CODE>
        <COUNTRY_CODE>643</COUNTRY_CODE>
        <BILCURRENCY_CODE>643</BILCURRENCY_CODE>
    </record>
    <record>
        <EFFECTIVE_DATE>20231022</EFFECTIVE_DATE>
        <MEMBER_ID>70230040101</MEMBER_ID>
        <LO_RANGE>2200040600000000000</LO_RANGE>
        <HI_RANGE>2200040639999999999</HI_RANGE>
        <BANK_NAME>Russian Standard</BANK_NAME>
        <PRODUCT_CODE>PRD</PRODUCT_CODE>
        <COUNTRY_CODE>643</COUNTRY_CODE>
        <BILCURRENCY_CODE>643</BILCURRENCY_CODE>
    </record>
    <record>
        <EFFECTIVE_DATE>20231022</EFFECTIVE_DATE>
        <MEMBER_ID>70230040101</MEMBER_ID>
        <LO_RANGE>2200040640000000000</LO_RANGE>
        <HI_RANGE>2200040669999999999</HI_RANGE>
        <BANK_NAME>Russian Standard</BANK_NAME>
        <PRODUCT_CODE>PRD</PRODUCT_CODE>
        <COUNTRY_CODE>643</COUNTRY_CODE>
        <BILCURRENCY_CODE>643</BILCURRENCY_CODE>
    </record>
    <record>
        <EFFECTIVE_DATE>20231022</EFFECTIVE_DATE>
        <MEMBER_ID>70230040101</MEMBER_ID>
        <LO_RANGE>2200040670000000000</LO_RANGE>
        <HI_RANGE>2200040699999999999</HI_RANGE>
        <BANK_NAME>Russian Standard</BANK_NAME>
        <PRODUCT_CODE>PRD</PRODUCT_CODE>
        <COUNTRY_CODE>643</COUNTRY_CODE>
        <BILCURRENCY_CODE>643</BILCURRENCY_CODE>
    </record>
    <record>
        <EFFECTIVE_DATE>20231022</EFFECTIVE_DATE>
        <MEMBER_ID>70230040103</MEMBER_ID>
        <LO_RANGE>2200040800000000000</LO_RANGE>
        <HI_RANGE>2200040899999999999</HI_RANGE>
        <BANK_NAME>Russian Standard</BANK_NAME>
        <PRODUCT_CODE>MDT</PRODUCT_CODE>
        <COUNTRY_CODE>643</COUNTRY_CODE>
        <BILCURRENCY_CODE>643</BILCURRENCY_CODE>
    </record>
    <record>
        <EFFECTIVE_DATE>20231022</EFFECTIVE_DATE>
        <MEMBER_ID>70230040103</MEMBER_ID>
        <LO_RANGE>2200040900000000000</LO_RANGE>
        <HI_RANGE>2200040999999999999</HI_RANGE>
        <BANK_NAME>Russian Standard</BANK_NAME>
        <PRODUCT_CODE>TKN</PRODUCT_CODE>
        <COUNTRY_CODE>643</COUNTRY_CODE>
        <BILCURRENCY_CODE>643</BILCURRENCY_CODE>
    </record>
    <record>
        <EFFECTIVE_DATE>20231022</EFFECTIVE_DATE>
        <MEMBER_ID>70240050101</MEMBER_ID>
        <LO_RANGE>2200050100000000000</LO_RANGE>
        <HI_RANGE>2200050199999999999</HI_RANGE>
        <BANK_NAME>Bank Otkritie Financial Corporation</BANK_NAME>
        <PRODUCT_CODE>MDT</PRODUCT_CODE>
        <COUNTRY_CODE>643</COUNTRY_CODE>
        <BILCURRENCY_CODE>643</BILCURRENCY_CODE>
    </record>
    <record>
        <EFFECTIVE_DATE>20231022</EFFECTIVE_DATE>
        <MEMBER_ID>70240050101</MEMBER_ID>
        <LO_RANGE>2200050200000000000</LO_RANGE>
        <HI_RANGE>2200050299999999999</HI_RANGE>
        <BANK_NAME>Bank Otkritie Financial Corporation</BANK_NAME>
        <PRODUCT_CODE>MDT</PRODUCT_CODE>
        <COUNTRY_CODE>643</COUNTRY_CODE>
        <BILCURRENCY_CODE>643</BILCURRENCY_CODE>
    </record>
    <record>
        <EFFECTIVE_DATE>20231022</EFFECTIVE_DATE>
        <MEMBER_ID>70240050101</MEMBER_ID>
        <LO_RANGE>2200050300000000000</LO_RANGE>
        <HI_RANGE>2200050399999999999</HI_RANGE>
        <BANK_NAME>Bank Otkritie Financial Corporation</BANK_NAME>
        <PRODUCT_CODE>MDP</PRODUCT_CODE>
        <COUNTRY_CODE>643</COUNTRY_CODE>
        <BILCURRENCY_CODE>643</BILCURRENCY_CODE>
    </record>
    <record>
        <EFFECTIVE_DATE>20231022</EFFECTIVE_DATE>
        <MEMBER_ID>70240050101</MEMBER_ID>
        <LO_RANGE>2200050400000000000</LO_RANGE>
        <HI_RANGE>2200050499999999999</HI_RANGE>
        <BANK_NAME>Bank Otkritie Financial Corporation</BANK_NAME>
        <PRODUCT_CODE>MDP</PRODUCT_CODE>
        <COUNTRY_CODE>643</COUNTRY_CODE>
        <BILCURRENCY_CODE>643</BILCURRENCY_CODE>
    </record>
    <record>
        <EFFECTIVE_DATE>20231022</EFFECTIVE_DATE>
        <MEMBER_ID>70240050101</MEMBER_ID>
        <LO_RANGE>2200050500000000000</LO_RANGE>
        <HI_RANGE>2200050599999999999</HI_RANGE>
        <BANK_NAME>Bank Otkritie Financial Corporation</BANK_NAME>
        <PRODUCT_CODE>MCD</PRODUCT_CODE>
        <COUNTRY_CODE>643</COUNTRY_CODE>
        <BILCURRENCY_CODE>643</BILCURRENCY_CODE>
    </record>
    <record>
        <EFFECTIVE_DATE>20231022</EFFECTIVE_DATE>
        <MEMBER_ID>70240050101</MEMBER_ID>
        <LO_RANGE>2200050600000000000</LO_RANGE>
        <HI_RANGE>2200050699999999999</HI_RANGE>
        <BANK_NAME>Bank Otkritie Financial Corporation</BANK_NAME>
        <PRODUCT_CODE>CCD</PRODUCT_CODE>
        <COUNTRY_CODE>643</COUNTRY_CODE>
        <BILCURRENCY_CODE>643</BILCURRENCY_CODE>
    </record>
    <record>
        <EFFECTIVE_DATE>20231022</EFFECTIVE_DATE>
        <MEMBER_ID>70080080101</MEMBER_ID>
        <LO_RANGE>2200080529999999000</LO_RANGE>
        <HI_RANGE>2200080549999999999</HI_RANGE>
        <BANK_NAME>BANK ROSSIYA</BANK_NAME>
        <PRODUCT_CODE>PRD</PRODUCT_CODE>
        <COUNTRY_CODE>643</COUNTRY_CODE>
        <BILCURRENCY_CODE>643</BILCURRENCY_CODE>
    </record>
    <record>
        <EFFECTIVE_DATE>20231022</EFFECTIVE_DATE>
        <MEMBER_ID>70080080101</MEMBER_ID>
        <LO_RANGE>2200080600000000000</LO_RANGE>
        <HI_RANGE>2200080600000099999</HI_RANGE>
        <BANK_NAME>BANK ROSSIYA</BANK_NAME>
        <PRODUCT_CODE>PRD</PRODUCT_CODE>
        <COUNTRY_CODE>643</COUNTRY_CODE>
        <BILCURRENCY_CODE>643</BILCURRENCY_CODE>
    </record>
    <record>
        <EFFECTIVE_DATE>20231022</EFFECTIVE_DATE>
        <MEMBER_ID>70080080101</MEMBER_ID>
        <LO_RANGE>2200080629999999000</LO_RANGE>
        <HI_RANGE>2200080644999999999</HI_RANGE>
        <BANK_NAME>BANK ROSSIYA</BANK_NAME>
        <PRODUCT_CODE>PRD</PRODUCT_CODE>
        <COUNTRY_CODE>643</COUNTRY_CODE>
        <BILCURRENCY_CODE>643</BILCURRENCY_CODE>
    </record>
    <record>
        <EFFECTIVE_DATE>20231022</EFFECTIVE_DATE>
        <MEMBER_ID>70080080101</MEMBER_ID>
        <LO_RANGE>2200080645000000000</LO_RANGE>
        <HI_RANGE>2200080645999999999</HI_RANGE>
        <BANK_NAME>BANK ROSSIYA</BANK_NAME>
        <PRODUCT_CODE>PRD</PRODUCT_CODE>
        <COUNTRY_CODE>643</COUNTRY_CODE>
        <BILCURRENCY_CODE>643</BILCURRENCY_CODE>
    </record>
    <record>
        <EFFECTIVE_DATE>20231022</EFFECTIVE_DATE>
        <MEMBER_ID>70080080101</MEMBER_ID>
        <LO_RANGE>2200080646000000000</LO_RANGE>
        <HI_RANGE>2200080648999999999</HI_RANGE>
        <BANK_NAME>BANK ROSSIYA</BANK_NAME>
        <PRODUCT_CODE>PRD</PRODUCT_CODE>
        <COUNTRY_CODE>643</COUNTRY_CODE>
        <BILCURRENCY_CODE>643</BILCURRENCY_CODE>
    </record>
    <record>
        <EFFECTIVE_DATE>20231022</EFFECTIVE_DATE>
        <MEMBER_ID>70080080101</MEMBER_ID>
        <LO_RANGE>2200080649000000000</LO_RANGE>
        <HI_RANGE>2200080649999999999</HI_RANGE>
        <BANK_NAME>BANK ROSSIYA</BANK_NAME>
        <PRODUCT_CODE>PRD</PRODUCT_CODE>
        <COUNTRY_CODE>643</COUNTRY_CODE>
        <BILCURRENCY_CODE>643</BILCURRENCY_CODE>
    </record>
    <record>
        <EFFECTIVE_DATE>20231022</EFFECTIVE_DATE>
        <MEMBER_ID>70080080101</MEMBER_ID>
        <LO_RANGE>2200080700000000000</LO_RANGE>
        <HI_RANGE>2200080799999999999</HI_RANGE>
        <BANK_NAME>BANK ROSSIYA</BANK_NAME>
        <PRODUCT_CODE>TKN</PRODUCT_CODE>
        <COUNTRY_CODE>643</COUNTRY_CODE>
        <BILCURRENCY_CODE>643</BILCURRENCY_CODE>
    </record>
    <record>
        <EFFECTIVE_DATE>20231022</EFFECTIVE_DATE>
        <MEMBER_ID>70080080101</MEMBER_ID>
        <LO_RANGE>2200080800000000000</LO_RANGE>
        <HI_RANGE>2200080800000099999</HI_RANGE>
        <BANK_NAME>BANK ROSSIYA</BANK_NAME>
        <PRODUCT_CODE>MSA</PRODUCT_CODE>
        <COUNTRY_CODE>643</COUNTRY_CODE>
        <BILCURRENCY_CODE>643</BILCURRENCY_CODE>
    </record>
    <record>
        <EFFECTIVE_DATE>20231022</EFFECTIVE_DATE>
        <MEMBER_ID>70080080101</MEMBER_ID>
        <LO_RANGE>2200080829999999000</LO_RANGE>
        <HI_RANGE>2200080830999999999</HI_RANGE>
        <BANK_NAME>BANK ROSSIYA</BANK_NAME>
        <PRODUCT_CODE>MSA</PRODUCT_CODE>
        <COUNTRY_CODE>643</COUNTRY_CODE>
        <BILCURRENCY_CODE>643</BILCURRENCY_CODE>
    </record>
    <record>
        <EFFECTIVE_DATE>20231022</EFFECTIVE_DATE>
        <MEMBER_ID>70080080101</MEMBER_ID>
        <LO_RANGE>2200080831000000000</LO_RANGE>
        <HI_RANGE>2200080849999999999</HI_RANGE>
        <BANK_NAME>BANK ROSSIYA</BANK_NAME>
        <PRODUCT_CODE>MSA</PRODUCT_CODE>
        <COUNTRY_CODE>643</COUNTRY_CODE>
        <BILCURRENCY_CODE>643</BILCURRENCY_CODE>
    </record>
    <record>
        <EFFECTIVE_DATE>20231022</EFFECTIVE_DATE>
        <MEMBER_ID>70770640102</MEMBER_ID>
        <LO_RANGE>2200640187700000000</LO_RANGE>
        <HI_RANGE>2200640187999999999</HI_RANGE>
        <BANK_NAME>Bank Kazani</BANK_NAME>
        <PRODUCT_CODE>MCB</PRODUCT_CODE>
        <COUNTRY_CODE>643</COUNTRY_CODE>
        <BILCURRENCY_CODE>643</BILCURRENCY_CODE>
    </record>
    <record>
        <EFFECTIVE_DATE>20231022</EFFECTIVE_DATE>
        <MEMBER_ID>70770640102</MEMBER_ID>
        <LO_RANGE>2200640193300000000</LO_RANGE>
        <HI_RANGE>2200640193899999999</HI_RANGE>
        <BANK_NAME>Bank Kazani</BANK_NAME>
        <PRODUCT_CODE>MCD</PRODUCT_CODE>
        <COUNTRY_CODE>643</COUNTRY_CODE>
        <BILCURRENCY_CODE>643</BILCURRENCY_CODE>
    </record>
    <record>
        <EFFECTIVE_DATE>20231022</EFFECTIVE_DATE>
        <MEMBER_ID>70770640102</MEMBER_ID>
        <LO_RANGE>2200640200000000000</LO_RANGE>
        <HI_RANGE>2200640209999999999</HI_RANGE>
        <BANK_NAME>Bank Kazani</BANK_NAME>
        <PRODUCT_CODE>CCD</PRODUCT_CODE>
        <COUNTRY_CODE>643</COUNTRY_CODE>
        <BILCURRENCY_CODE>643</BILCURRENCY_CODE>
    </record>
    <record>
        <EFFECTIVE_DATE>20231022</EFFECTIVE_DATE>
        <MEMBER_ID>70770640102</MEMBER_ID>
        <LO_RANGE>2200640210000000000</LO_RANGE>
        <HI_RANGE>2200640219999999999</HI_RANGE>
        <BANK_NAME>Bank Kazani</BANK_NAME>
        <PRODUCT_CODE>CCD</PRODUCT_CODE>
        <COUNTRY_CODE>643</COUNTRY_CODE>
        <BILCURRENCY_CODE>643</BILCURRENCY_CODE>
    </record>
    <record>
        <EFFECTIVE_DATE>20231022</EFFECTIVE_DATE>
        <MEMBER_ID>70770640102</MEMBER_ID>
        <LO_RANGE>2200640220000000000</LO_RANGE>
        <HI_RANGE>2200640229999999999</HI_RANGE>
        <BANK_NAME>Bank Kazani</BANK_NAME>
        <PRODUCT_CODE>CCD</PRODUCT_CODE>
        <COUNTRY_CODE>643</COUNTRY_CODE>
        <BILCURRENCY_CODE>643</BILCURRENCY_CODE>
    </record>
    <record>
        <EFFECTIVE_DATE>20231022</EFFECTIVE_DATE>
        <MEMBER_ID>70770640102</MEMBER_ID>
        <LO_RANGE>2200640230000000000</LO_RANGE>
        <HI_RANGE>2200640239999999999</HI_RANGE>
        <BANK_NAME>Bank Kazani</BANK_NAME>
        <PRODUCT_CODE>CCD</PRODUCT_CODE>
        <COUNTRY_CODE>643</COUNTRY_CODE>
        <BILCURRENCY_CODE>643</BILCURRENCY_CODE>
    </record>
    <record>
        <EFFECTIVE_DATE>20231022</EFFECTIVE_DATE>
        <MEMBER_ID>70770640102</MEMBER_ID>
        <LO_RANGE>2200640240000000000</LO_RANGE>
        <HI_RANGE>2200640249999999999</HI_RANGE>
        <BANK_NAME>Bank Kazani</BANK_NAME>
        <PRODUCT_CODE>CCD</PRODUCT_CODE>
        <COUNTRY_CODE>643</COUNTRY_CODE>
        <BILCURRENCY_CODE>643</BILCURRENCY_CODE>
    </record>
    <record>
        <EFFECTIVE_DATE>20231022</EFFECTIVE_DATE>
        <MEMBER_ID>70770640102</MEMBER_ID>
        <LO_RANGE>2200640250000000000</LO_RANGE>
        <HI_RANGE>2200640259999999999</HI_RANGE>
        <BANK_NAME>Bank Kazani</BANK_NAME>
        <PRODUCT_CODE>CCD</PRODUCT_CODE>
        <COUNTRY_CODE>643</COUNTRY_CODE>
        <BILCURRENCY_CODE>643</BILCURRENCY_CODE>
    </record>
    <record>
        <EFFECTIVE_DATE>20231022</EFFECTIVE_DATE>
        <MEMBER_ID>70850720101</MEMBER_ID>
        <LO_RANGE>2200720501000000000</LO_RANGE>
        <HI_RANGE>2200720501999999999</HI_RANGE>
        <BANK_NAME>Banca Intesa</BANK_NAME>
        <PRODUCT_CODE>MSA</PRODUCT_CODE>
        <COUNTRY_CODE>643</COUNTRY_CODE>
        <BILCURRENCY_CODE>840</BILCURRENCY_CODE>
    </record>
    <record>
        <EFFECTIVE_DATE>20231022</EFFECTIVE_DATE>
        <MEMBER_ID>70850720101</MEMBER_ID>
        <LO_RANGE>2200720502000000000</LO_RANGE>
        <HI_RANGE>2200720502999999999</HI_RANGE>
        <BANK_NAME>Banca Intesa</BANK_NAME>
        <PRODUCT_CODE>MSA</PRODUCT_CODE>
        <COUNTRY_CODE>643</COUNTRY_CODE>
        <BILCURRENCY_CODE>978</BILCURRENCY_CODE>
    </record>
    <record>
        <EFFECTIVE_DATE>20231022</EFFECTIVE_DATE>
        <MEMBER_ID>70850720101</MEMBER_ID>
        <LO_RANGE>2200720590000000000</LO_RANGE>
        <HI_RANGE>2200720590999999999</HI_RANGE>
        <BANK_NAME>Banca Intesa</BANK_NAME>
        <PRODUCT_CODE>MSA</PRODUCT_CODE>
        <COUNTRY_CODE>643</COUNTRY_CODE>
        <BILCURRENCY_CODE>643</BILCURRENCY_CODE>
    </record>
    <record>
        <EFFECTIVE_DATE>20231022</EFFECTIVE_DATE>
        <MEMBER_ID>70850720101</MEMBER_ID>
        <LO_RANGE>2200720591000000000</LO_RANGE>
        <HI_RANGE>2200720591999999999</HI_RANGE>
        <BANK_NAME>Banca Intesa</BANK_NAME>
        <PRODUCT_CODE>MSA</PRODUCT_CODE>
        <COUNTRY_CODE>643</COUNTRY_CODE>
        <BILCURRENCY_CODE>840</BILCURRENCY_CODE>
    </record>
    <record>
        <EFFECTIVE_DATE>20231022</EFFECTIVE_DATE>
        <MEMBER_ID>70850720101</MEMBER_ID>
        <LO_RANGE>2200720592000000000</LO_RANGE>
        <HI_RANGE>2200720592999999999</HI_RANGE>
        <BANK_NAME>Banca Intesa</BANK_NAME>
        <PRODUCT_CODE>MSA</PRODUCT_CODE>
        <COUNTRY_CODE>643</COUNTRY_CODE>
        <BILCURRENCY_CODE>978</BILCURRENCY_CODE>
    </record>
    <record>
        <EFFECTIVE_DATE>20231022</EFFECTIVE_DATE>
        <MEMBER_ID>70850720101</MEMBER_ID>
        <LO_RANGE>2200720600000000000</LO_RANGE>
        <HI_RANGE>2200720699999999999</HI_RANGE>
        <BANK_NAME>Banca Intesa</BANK_NAME>
        <PRODUCT_CODE>TKN</PRODUCT_CODE>
        <COUNTRY_CODE>643</COUNTRY_CODE>
        <BILCURRENCY_CODE>643</BILCURRENCY_CODE>
    </record>
    <record>
        <EFFECTIVE_DATE>20231022</EFFECTIVE_DATE>
        <MEMBER_ID>70880730101</MEMBER_ID>
        <LO_RANGE>2200730230000000000</LO_RANGE>
        <HI_RANGE>2200730239999999999</HI_RANGE>
        <BANK_NAME>QIWI Bank</BANK_NAME>
        <PRODUCT_CODE>CDP</PRODUCT_CODE>
        <COUNTRY_CODE>643</COUNTRY_CODE>
        <BILCURRENCY_CODE>643</BILCURRENCY_CODE>
    </record>
    <record>
        <EFFECTIVE_DATE>20231022</EFFECTIVE_DATE>
        <MEMBER_ID>70880730101</MEMBER_ID>
        <LO_RANGE>2200730240000000000</LO_RANGE>
        <HI_RANGE>2200730259999999999</HI_RANGE>
        <BANK_NAME>QIWI Bank</BANK_NAME>
        <PRODUCT_CODE>CDP</PRODUCT_CODE>
        <COUNTRY_CODE>643</COUNTRY_CODE>
        <BILCURRENCY_CODE>643</BILCURRENCY_CODE>
    </record>
    <record>
        <EFFECTIVE_DATE>20231022</EFFECTIVE_DATE>
        <MEMBER_ID>70880730101</MEMBER_ID>
        <LO_RANGE>2200730260000000000</LO_RANGE>
        <HI_RANGE>2200730299999999999</HI_RANGE>
        <BANK_NAME>QIWI Bank</BANK_NAME>
        <PRODUCT_CODE>CDP</PRODUCT_CODE>
        <COUNTRY_CODE>643</COUNTRY_CODE>
        <BILCURRENCY_CODE>643</BILCURRENCY_CODE>
    </record>
    <record>
        <EFFECTIVE_DATE>20231022</EFFECTIVE_DATE>
        <MEMBER_ID>70880730101</MEMBER_ID>
        <LO_RANGE>2200730330000000000</LO_RANGE>
        <HI_RANGE>2200730339999999999</HI_RANGE>
        <BANK_NAME>QIWI Bank</BANK_NAME>
        <PRODUCT_CODE>CDP</PRODUCT_CODE>
        <COUNTRY_CODE>643</COUNTRY_CODE>
        <BILCURRENCY_CODE>643</BILCURRENCY_CODE>
    </record>
    <record>
        <EFFECTIVE_DATE>20231022</EFFECTIVE_DATE>
        <MEMBER_ID>70880730101</MEMBER_ID>
        <LO_RANGE>2200730340000000000</LO_RANGE>
        <HI_RANGE>2200730349999999999</HI_RANGE>
        <BANK_NAME>QIWI Bank</BANK_NAME>
        <PRODUCT_CODE>CDP</PRODUCT_CODE>
        <COUNTRY_CODE>643</COUNTRY_CODE>
        <BILCURRENCY_CODE>643</BILCURRENCY_CODE>
    </record>
    <record>
        <EFFECTIVE_DATE>20231022</EFFECTIVE_DATE>
        <MEMBER_ID>70870760102</MEMBER_ID>
        <LO_RANGE>2200760334100000000</LO_RANGE>
        <HI_RANGE>2200760334299999999</HI_RANGE>
        <BANK_NAME>RNCB</BANK_NAME>
        <PRODUCT_CODE>CCD</PRODUCT_CODE>
        <COUNTRY_CODE>643</COUNTRY_CODE>
        <BILCURRENCY_CODE>643</BILCURRENCY_CODE>
    </record>
    <record>
        <EFFECTIVE_DATE>20231022</EFFECTIVE_DATE>
        <MEMBER_ID>70870760102</MEMBER_ID>
        <LO_RANGE>2200760334400000000</LO_RANGE>
        <HI_RANGE>2200760334799999999</HI_RANGE>
        <BANK_NAME>RNCB</BANK_NAME>
        <PRODUCT_CODE>CCD</PRODUCT_CODE>
        <COUNTRY_CODE>643</COUNTRY_CODE>
        <BILCURRENCY_CODE>643</BILCURRENCY_CODE>
    </record>
    <record>
        <EFFECTIVE_DATE>20231022</EFFECTIVE_DATE>
        <MEMBER_ID>89005000023</MEMBER_ID>
        <LO_RANGE>9112711300000000000</LO_RANGE>
        <HI_RANGE>9112711399999999999</HI_RANGE>
        <BANK_NAME>Sber bank</BANK_NAME>
        <PRODUCT_CODE>CCD</PRODUCT_CODE>
        <COUNTRY_CODE>112</COUNTRY_CODE>
        <BILCURRENCY_CODE>933</BILCURRENCY_CODE>
    </record>
    <record>
        <EFFECTIVE_DATE>20231022</EFFECTIVE_DATE>
        <MEMBER_ID>89005000023</MEMBER_ID>
        <LO_RANGE>9112711400000000000</LO_RANGE>
        <HI_RANGE>9112711499999999999</HI_RANGE>
        <BANK_NAME>Sber bank</BANK_NAME>
        <PRODUCT_CODE>CCD</PRODUCT_CODE>
        <COUNTRY_CODE>112</COUNTRY_CODE>
        <BILCURRENCY_CODE>933</BILCURRENCY_CODE>
    </record>
    <record>
        <EFFECTIVE_DATE>20231022</EFFECTIVE_DATE>
        <MEMBER_ID>89005000023</MEMBER_ID>
        <LO_RANGE>9112711500000000000</LO_RANGE>
        <HI_RANGE>9112711599999999999</HI_RANGE>
        <BANK_NAME>Sber bank</BANK_NAME>
        <PRODUCT_CODE>CCD</PRODUCT_CODE>
        <COUNTRY_CODE>112</COUNTRY_CODE>
        <BILCURRENCY_CODE>933</BILCURRENCY_CODE>
    </record>
    <record>
        <EFFECTIVE_DATE>20231022</EFFECTIVE_DATE>
        <MEMBER_ID>89005000023</MEMBER_ID>
        <LO_RANGE>9112711600000000000</LO_RANGE>
        <HI_RANGE>9112711699999999999</HI_RANGE>
        <BANK_NAME>Sber bank</BANK_NAME>
        <PRODUCT_CODE>CCD</PRODUCT_CODE>
        <COUNTRY_CODE>112</COUNTRY_CODE>
        <BILCURRENCY_CODE>933</BILCURRENCY_CODE>
    </record>
    <record>
        <EFFECTIVE_DATE>20231022</EFFECTIVE_DATE>
        <MEMBER_ID>89005000023</MEMBER_ID>
        <LO_RANGE>9112711700000000000</LO_RANGE>
        <HI_RANGE>9112711799999999999</HI_RANGE>
        <BANK_NAME>Sber bank</BANK_NAME>
        <PRODUCT_CODE>CCD</PRODUCT_CODE>
        <COUNTRY_CODE>112</COUNTRY_CODE>
        <BILCURRENCY_CODE>933</BILCURRENCY_CODE>
    </record>
    <record>
        <EFFECTIVE_DATE>20231022</EFFECTIVE_DATE>
        <MEMBER_ID>89005000023</MEMBER_ID>
        <LO_RANGE>9112711800000000000</LO_RANGE>
        <HI_RANGE>9112711899999999999</HI_RANGE>
        <BANK_NAME>Sber bank</BANK_NAME>
        <PRODUCT_CODE>CCD</PRODUCT_CODE>
        <COUNTRY_CODE>112</COUNTRY_CODE>
        <BILCURRENCY_CODE>933</BILCURRENCY_CODE>
    </record>
    <record>
        <EFFECTIVE_DATE>20231022</EFFECTIVE_DATE>
        <MEMBER_ID>89005000006</MEMBER_ID>
        <LO_RANGE>9112712000000000000</LO_RANGE>
        <HI_RANGE>9112712099999999999</HI_RANGE>
        <BANK_NAME>"Bank Dabrabyt" JSC</BANK_NAME>
        <PRODUCT_CODE>CCD</PRODUCT_CODE>
        <COUNTRY_CODE>112</COUNTRY_CODE>
        <BILCURRENCY_CODE>933</BILCURRENCY_CODE>
    </record>
    <record>
        <EFFECTIVE_DATE>20231022</EFFECTIVE_DATE>
        <MEMBER_ID>89005000006</MEMBER_ID>
        <LO_RANGE>9112712100000000000</LO_RANGE>
        <HI_RANGE>9112712199999999999</HI_RANGE>
        <BANK_NAME>"Bank Dabrabyt" JSC</BANK_NAME>
        <PRODUCT_CODE>CCD</PRODUCT_CODE>
        <COUNTRY_CODE>112</COUNTRY_CODE>
        <BILCURRENCY_CODE>933</BILCURRENCY_CODE>
    </record>
    <record>
        <EFFECTIVE_DATE>20231022</EFFECTIVE_DATE>
        <MEMBER_ID>89005000006</MEMBER_ID>
        <LO_RANGE>9112712200000000000</LO_RANGE>
        <HI_RANGE>9112712299999999999</HI_RANGE>
        <BANK_NAME>"Bank Dabrabyt" JSC</BANK_NAME>
        <PRODUCT_CODE>CCD</PRODUCT_CODE>
        <COUNTRY_CODE>112</COUNTRY_CODE>
        <BILCURRENCY_CODE>933</BILCURRENCY_CODE>
    </record>
    <record>
        <EFFECTIVE_DATE>20231022</EFFECTIVE_DATE>
        <MEMBER_ID>89005000006</MEMBER_ID>
        <LO_RANGE>9112713000000000000</LO_RANGE>
        <HI_RANGE>9112713099999999999</HI_RANGE>
        <BANK_NAME>"Bank Dabrabyt" JSC</BANK_NAME>
        <PRODUCT_CODE>CCD</PRODUCT_CODE>
        <COUNTRY_CODE>112</COUNTRY_CODE>
        <BILCURRENCY_CODE>933</BILCURRENCY_CODE>
    </record>
    <record>
        <EFFECTIVE_DATE>20231022</EFFECTIVE_DATE>
        <MEMBER_ID>89005000005</MEMBER_ID>
        <LO_RANGE>9112714000000000000</LO_RANGE>
        <HI_RANGE>9112714099999999999</HI_RANGE>
        <BANK_NAME>Bank BelVEB JSC</BANK_NAME>
        <PRODUCT_CODE>CCD</PRODUCT_CODE>
        <COUNTRY_CODE>112</COUNTRY_CODE>
        <BILCURRENCY_CODE>933</BILCURRENCY_CODE>
    </record>
    <record>
        <EFFECTIVE_DATE>20231022</EFFECTIVE_DATE>
        <MEMBER_ID>89005000005</MEMBER_ID>
        <LO_RANGE>9112714100000000000</LO_RANGE>
        <HI_RANGE>9112714199999999999</HI_RANGE>
        <BANK_NAME>Bank BelVEB JSC</BANK_NAME>
        <PRODUCT_CODE>CCD</PRODUCT_CODE>
        <COUNTRY_CODE>112</COUNTRY_CODE>
        <BILCURRENCY_CODE>933</BILCURRENCY_CODE>
    </record>
    <record>
        <EFFECTIVE_DATE>20231022</EFFECTIVE_DATE>
        <MEMBER_ID>89005000005</MEMBER_ID>
        <LO_RANGE>9112715000000000000</LO_RANGE>
        <HI_RANGE>9112715099999999999</HI_RANGE>
        <BANK_NAME>Bank BelVEB JSC</BANK_NAME>
        <PRODUCT_CODE>CCD</PRODUCT_CODE>
        <COUNTRY_CODE>112</COUNTRY_CODE>
        <BILCURRENCY_CODE>933</BILCURRENCY_CODE>
    </record>
    <record>
        <EFFECTIVE_DATE>20231022</EFFECTIVE_DATE>
        <MEMBER_ID>89005000005</MEMBER_ID>
        <LO_RANGE>9112715100000000000</LO_RANGE>
        <HI_RANGE>9112715199999999999</HI_RANGE>
        <BANK_NAME>Bank BelVEB JSC</BANK_NAME>
        <PRODUCT_CODE>CCD</PRODUCT_CODE>
        <COUNTRY_CODE>112</COUNTRY_CODE>
        <BILCURRENCY_CODE>933</BILCURRENCY_CODE>
    </record>
    <record>
        <EFFECTIVE_DATE>20231022</EFFECTIVE_DATE>
        <MEMBER_ID>89005000005</MEMBER_ID>
        <LO_RANGE>9112715200000000000</LO_RANGE>
        <HI_RANGE>9112715299999999999</HI_RANGE>
        <BANK_NAME>Bank BelVEB JSC</BANK_NAME>
        <PRODUCT_CODE>CCD</PRODUCT_CODE>
        <COUNTRY_CODE>112</COUNTRY_CODE>
        <BILCURRENCY_CODE>933</BILCURRENCY_CODE>
    </record>
    <record>
        <EFFECTIVE_DATE>20231022</EFFECTIVE_DATE>
        <MEMBER_ID>89005000005</MEMBER_ID>
        <LO_RANGE>9112715300000000000</LO_RANGE>
        <HI_RANGE>9112715399999999999</HI_RANGE>
        <BANK_NAME>Bank BelVEB JSC</BANK_NAME>
        <PRODUCT_CODE>CCD</PRODUCT_CODE>
        <COUNTRY_CODE>112</COUNTRY_CODE>
        <BILCURRENCY_CODE>933</BILCURRENCY_CODE>
    </record>
    <record>
        <EFFECTIVE_DATE>20231022</EFFECTIVE_DATE>
        <MEMBER_ID>89005000005</MEMBER_ID>
        <LO_RANGE>9112880000000000000</LO_RANGE>
        <HI_RANGE>9112889999999999999</HI_RANGE>
        <BANK_NAME>Bank BelVEB JSC</BANK_NAME>
        <PRODUCT_CODE>CCD</PRODUCT_CODE>
        <COUNTRY_CODE>112</COUNTRY_CODE>
        <BILCURRENCY_CODE>933</BILCURRENCY_CODE>
    </record>
    <record>
        <EFFECTIVE_DATE>20231022</EFFECTIVE_DATE>
        <MEMBER_ID>89003000001</MEMBER_ID>
        <LO_RANGE>9417000100000000000</LO_RANGE>
        <HI_RANGE>9417000199999999999</HI_RANGE>
        <BANK_NAME>CJSC "Kyrgyz Investment and Credit Bank"</BANK_NAME>
        <PRODUCT_CODE>CCD</PRODUCT_CODE>
        <COUNTRY_CODE>417</COUNTRY_CODE>
        <BILCURRENCY_CODE>417</BILCURRENCY_CODE>
    </record>
    <record>
        <EFFECTIVE_DATE>20231022</EFFECTIVE_DATE>
        <MEMBER_ID>89003000002</MEMBER_ID>
        <LO_RANGE>9417000200000000000</LO_RANGE>
        <HI_RANGE>9417000299999999999</HI_RANGE>
        <BANK_NAME>OJSC "BAKAI Bank"</BANK_NAME>
        <PRODUCT_CODE>CCD</PRODUCT_CODE>
        <COUNTRY_CODE>417</COUNTRY_CODE>
        <BILCURRENCY_CODE>417</BILCURRENCY_CODE>
    </record>
    <record>
        <EFFECTIVE_DATE>20231022</EFFECTIVE_DATE>
        <MEMBER_ID>89003000003</MEMBER_ID>
        <LO_RANGE>9417000400000000000</LO_RANGE>
        <HI_RANGE>9417000499999999999</HI_RANGE>
        <BANK_NAME>OJSC "RSK Bank"</BANK_NAME>
        <PRODUCT_CODE>CCD</PRODUCT_CODE>
        <COUNTRY_CODE>417</COUNTRY_CODE>
        <BILCURRENCY_CODE>417</BILCURRENCY_CODE>
    </record>
    <record>
        <EFFECTIVE_DATE>20231022</EFFECTIVE_DATE>
        <MEMBER_ID>89003000027</MEMBER_ID>
        <LO_RANGE>9417000500000000000</LO_RANGE>
        <HI_RANGE>9417000599999999999</HI_RANGE>
        <BANK_NAME>"Green Telecom Service" LLC</BANK_NAME>
        <PRODUCT_CODE>CCD</PRODUCT_CODE>
        <COUNTRY_CODE>417</COUNTRY_CODE>
        <BILCURRENCY_CODE>417</BILCURRENCY_CODE>
    </record>
    <record>
        <EFFECTIVE_DATE>20231022</EFFECTIVE_DATE>
        <MEMBER_ID>89003000005</MEMBER_ID>
        <LO_RANGE>9417000600000000000</LO_RANGE>
        <HI_RANGE>9417000699999999999</HI_RANGE>
        <BANK_NAME>CJSC "EcoIslamicBank"</BANK_NAME>
        <PRODUCT_CODE>CCD</PRODUCT_CODE>
        <COUNTRY_CODE>417</COUNTRY_CODE>
        <BILCURRENCY_CODE>417</BILCURRENCY_CODE>
    </record>
    <record>
        <EFFECTIVE_DATE>20231022</EFFECTIVE_DATE>
        <MEMBER_ID>89003000006</MEMBER_ID>
        <LO_RANGE>9417000700000000000</LO_RANGE>
        <HI_RANGE>9417000799999999999</HI_RANGE>
        <BANK_NAME>OJSC "Dos-Kredobank"</BANK_NAME>
        <PRODUCT_CODE>CCD</PRODUCT_CODE>
        <COUNTRY_CODE>417</COUNTRY_CODE>
        <BILCURRENCY_CODE>417</BILCURRENCY_CODE>
    </record>
    <record>
        <EFFECTIVE_DATE>20231022</EFFECTIVE_DATE>
        <MEMBER_ID>89003000008</MEMBER_ID>
        <LO_RANGE>9417000900000000000</LO_RANGE>
        <HI_RANGE>9417000999999999999</HI_RANGE>
        <BANK_NAME>OJSC "Commercial bank KYRGYZSTAN"</BANK_NAME>
        <PRODUCT_CODE>CCD</PRODUCT_CODE>
        <COUNTRY_CODE>417</COUNTRY_CODE>
        <BILCURRENCY_CODE>417</BILCURRENCY_CODE>
    </record>
    <record>
        <EFFECTIVE_DATE>20231022</EFFECTIVE_DATE>
        <MEMBER_ID>89003000009</MEMBER_ID>
        <LO_RANGE>9417001100000000000</LO_RANGE>
        <HI_RANGE>9417001199999999999</HI_RANGE>
        <BANK_NAME>CJSC "Bank of Asia"</BANK_NAME>
        <PRODUCT_CODE>CCD</PRODUCT_CODE>
        <COUNTRY_CODE>417</COUNTRY_CODE>
        <BILCURRENCY_CODE>417</BILCURRENCY_CODE>
    </record>
    <record>
        <EFFECTIVE_DATE>20231022</EFFECTIVE_DATE>
        <MEMBER_ID>89003000010</MEMBER_ID>
        <LO_RANGE>9417001200000000000</LO_RANGE>
        <HI_RANGE>9417001299999999999</HI_RANGE>
        <BANK_NAME>OJSC "Eurasian Savings Bank"</BANK_NAME>
        <PRODUCT_CODE>CCD</PRODUCT_CODE>
        <COUNTRY_CODE>417</COUNTRY_CODE>
        <BILCURRENCY_CODE>417</BILCURRENCY_CODE>
    </record>
    <record>
        <EFFECTIVE_DATE>20231022</EFFECTIVE_DATE>
        <MEMBER_ID>89003000011</MEMBER_ID>
        <LO_RANGE>9417001300000000000</LO_RANGE>
        <HI_RANGE>9417001399999999999</HI_RANGE>
        <BANK_NAME>OJSC "Keremet Bank"</BANK_NAME>
        <PRODUCT_CODE>CCD</PRODUCT_CODE>
        <COUNTRY_CODE>417</COUNTRY_CODE>
        <BILCURRENCY_CODE>417</BILCURRENCY_CODE>
    </record>
    <record>
        <EFFECTIVE_DATE>20231022</EFFECTIVE_DATE>
        <MEMBER_ID>89003000012</MEMBER_ID>
        <LO_RANGE>9417001400000000000</LO_RANGE>
        <HI_RANGE>9417001499999999999</HI_RANGE>
        <BANK_NAME>OJSC "FinanceCreditBank"</BANK_NAME>
        <PRODUCT_CODE>CCD</PRODUCT_CODE>
        <COUNTRY_CODE>417</COUNTRY_CODE>
        <BILCURRENCY_CODE>417</BILCURRENCY_CODE>
    </record>
    <record>
        <EFFECTIVE_DATE>20231022</EFFECTIVE_DATE>
        <MEMBER_ID>89003000013</MEMBER_ID>
        <LO_RANGE>9417001500000000000</LO_RANGE>
        <HI_RANGE>9417001599999999999</HI_RANGE>
        <BANK_NAME>OJSC "Halyk Bank Kyrgyzstan"</BANK_NAME>
        <PRODUCT_CODE>CCD</PRODUCT_CODE>
        <COUNTRY_CODE>417</COUNTRY_CODE>
        <BILCURRENCY_CODE>417</BILCURRENCY_CODE>
    </record>
    <record>
        <EFFECTIVE_DATE>20231022</EFFECTIVE_DATE>
        <MEMBER_ID>89003000014</MEMBER_ID>
        <LO_RANGE>9417001600000000000</LO_RANGE>
        <HI_RANGE>9417001699999999999</HI_RANGE>
        <BANK_NAME>CJSC "Kyrgyz-Swiss Bank"</BANK_NAME>
        <PRODUCT_CODE>CCD</PRODUCT_CODE>
        <COUNTRY_CODE>417</COUNTRY_CODE>
        <BILCURRENCY_CODE>417</BILCURRENCY_CODE>
    </record>
    <record>
        <EFFECTIVE_DATE>20231022</EFFECTIVE_DATE>
        <MEMBER_ID>89003000015</MEMBER_ID>
        <LO_RANGE>9417001700000000000</LO_RANGE>
        <HI_RANGE>9417001799999999999</HI_RANGE>
        <BANK_NAME>CJSC"Bai-Tushum" Bank</BANK_NAME>
        <PRODUCT_CODE>CCD</PRODUCT_CODE>
        <COUNTRY_CODE>417</COUNTRY_CODE>
        <BILCURRENCY_CODE>417</BILCURRENCY_CODE>
    </record>
    <record>
        <EFFECTIVE_DATE>20231022</EFFECTIVE_DATE>
        <MEMBER_ID>89003000016</MEMBER_ID>
        <LO_RANGE>9417001800000000000</LO_RANGE>
        <HI_RANGE>9417001899999999999</HI_RANGE>
        <BANK_NAME>CJSB JSCB "Tolubay"</BANK_NAME>
        <PRODUCT_CODE>CCD</PRODUCT_CODE>
        <COUNTRY_CODE>417</COUNTRY_CODE>
        <BILCURRENCY_CODE>417</BILCURRENCY_CODE>
    </record>
    <record>
        <EFFECTIVE_DATE>20231022</EFFECTIVE_DATE>
        <MEMBER_ID>89003000017</MEMBER_ID>
        <LO_RANGE>9417001900000000000</LO_RANGE>
        <HI_RANGE>9417001999999999999</HI_RANGE>
        <BANK_NAME>OJSC "Aiyl Bank"</BANK_NAME>
        <PRODUCT_CODE>CCD</PRODUCT_CODE>
        <COUNTRY_CODE>417</COUNTRY_CODE>
        <BILCURRENCY_CODE>417</BILCURRENCY_CODE>
    </record>
    <record>
        <EFFECTIVE_DATE>20231022</EFFECTIVE_DATE>
        <MEMBER_ID>89003000020</MEMBER_ID>
        <LO_RANGE>9417002200000000000</LO_RANGE>
        <HI_RANGE>9417002299999999999</HI_RANGE>
        <BANK_NAME>CJSC"FINCA Bank"</BANK_NAME>
        <PRODUCT_CODE>CCD</PRODUCT_CODE>
        <COUNTRY_CODE>417</COUNTRY_CODE>
        <BILCURRENCY_CODE>417</BILCURRENCY_CODE>
    </record>
    <record>
        <EFFECTIVE_DATE>20231022</EFFECTIVE_DATE>
        <MEMBER_ID>89004000008</MEMBER_ID>
        <LO_RANGE>5614680400000000000</LO_RANGE>
        <HI_RANGE>5614680499999999999</HI_RANGE>
        <BANK_NAME>JSCB "QishloqQurilishBank"</BANK_NAME>
        <PRODUCT_CODE>MCD</PRODUCT_CODE>
        <COUNTRY_CODE>860</COUNTRY_CODE>
        <BILCURRENCY_CODE>860</BILCURRENCY_CODE>
    </record>
    <record>
        <EFFECTIVE_DATE>20231022</EFFECTIVE_DATE>
        <MEMBER_ID>89004000017</MEMBER_ID>
        <LO_RANGE>5614680500000000000</LO_RANGE>
        <HI_RANGE>5614680599999999999</HI_RANGE>
        <BANK_NAME>PJSC "Davr-bank"</BANK_NAME>
        <PRODUCT_CODE>MCD</PRODUCT_CODE>
        <COUNTRY_CODE>860</COUNTRY_CODE>
        <BILCURRENCY_CODE>860</BILCURRENCY_CODE>
    </record>
    <record>
        <EFFECTIVE_DATE>20231022</EFFECTIVE_DATE>
        <MEMBER_ID>89004000026</MEMBER_ID>
        <LO_RANGE>5614680600000000000</LO_RANGE>
        <HI_RANGE>5614680699999999999</HI_RANGE>
        <BANK_NAME>JSC "ZIRAAT BANK"</BANK_NAME>
        <PRODUCT_CODE>MCD</PRODUCT_CODE>
        <COUNTRY_CODE>860</COUNTRY_CODE>
        <BILCURRENCY_CODE>860</BILCURRENCY_CODE>
    </record>
    <record>
        <EFFECTIVE_DATE>20231022</EFFECTIVE_DATE>
        <MEMBER_ID>89004000013</MEMBER_ID>
        <LO_RANGE>5614680700000000000</LO_RANGE>
        <HI_RANGE>5614680799999999999</HI_RANGE>
        <BANK_NAME>JSCB "Turonbank"</BANK_NAME>
        <PRODUCT_CODE>MCD</PRODUCT_CODE>
        <COUNTRY_CODE>860</COUNTRY_CODE>
        <BILCURRENCY_CODE>860</BILCURRENCY_CODE>
    </record>
    <record>
        <EFFECTIVE_DATE>20231022</EFFECTIVE_DATE>
        <MEMBER_ID>89004000029</MEMBER_ID>
        <LO_RANGE>5614680800000000000</LO_RANGE>
        <HI_RANGE>5614680899999999999</HI_RANGE>
        <BANK_NAME>JSC "Poytaht bank"</BANK_NAME>
        <PRODUCT_CODE>MCD</PRODUCT_CODE>
        <COUNTRY_CODE>860</COUNTRY_CODE>
        <BILCURRENCY_CODE>860</BILCURRENCY_CODE>
    </record>
    <record>
        <EFFECTIVE_DATE>20231022</EFFECTIVE_DATE>
        <MEMBER_ID>89004000018</MEMBER_ID>
        <LO_RANGE>5614680900000000000</LO_RANGE>
        <HI_RANGE>5614680999999999999</HI_RANGE>
        <BANK_NAME>JSCB "Asia Aliance Bank"</BANK_NAME>
        <PRODUCT_CODE>MCD</PRODUCT_CODE>
        <COUNTRY_CODE>860</COUNTRY_CODE>
        <BILCURRENCY_CODE>860</BILCURRENCY_CODE>
    </record>
    <record>
        <EFFECTIVE_DATE>20231022</EFFECTIVE_DATE>
        <MEMBER_ID>89004000020</MEMBER_ID>
        <LO_RANGE>5614681000000000000</LO_RANGE>
        <HI_RANGE>5614681099999999999</HI_RANGE>
        <BANK_NAME>PJSC "Universalbank"</BANK_NAME>
        <PRODUCT_CODE>MCD</PRODUCT_CODE>
        <COUNTRY_CODE>860</COUNTRY_CODE>
        <BILCURRENCY_CODE>860</BILCURRENCY_CODE>
    </record>
    <record>
        <EFFECTIVE_DATE>20231022</EFFECTIVE_DATE>
        <MEMBER_ID>89004000027</MEMBER_ID>
        <LO_RANGE>5614681100000000000</LO_RANGE>
        <HI_RANGE>5614681199999999999</HI_RANGE>
        <BANK_NAME>Affiliate bank "Saderot" Iran</BANK_NAME>
        <PRODUCT_CODE>MCD</PRODUCT_CODE>
        <COUNTRY_CODE>860</COUNTRY_CODE>
        <BILCURRENCY_CODE>860</BILCURRENCY_CODE>
    </record>
    <record>
        <EFFECTIVE_DATE>20231022</EFFECTIVE_DATE>
        <MEMBER_ID>89004000003</MEMBER_ID>
        <LO_RANGE>5614681200000000000</LO_RANGE>
        <HI_RANGE>5614681299999999999</HI_RANGE>
        <BANK_NAME>JSICB "Ipoteka-bank"</BANK_NAME>
        <PRODUCT_CODE>MCD</PRODUCT_CODE>
        <COUNTRY_CODE>860</COUNTRY_CODE>
        <BILCURRENCY_CODE>860</BILCURRENCY_CODE>
    </record>
    <record>
        <EFFECTIVE_DATE>20231022</EFFECTIVE_DATE>
        <MEMBER_ID>89004000006</MEMBER_ID>
        <LO_RANGE>5614681300000000000</LO_RANGE>
        <HI_RANGE>5614681399999999999</HI_RANGE>
        <BANK_NAME>JSCB "Mikrokreditbank"</BANK_NAME>
        <PRODUCT_CODE>MCD</PRODUCT_CODE>
        <COUNTRY_CODE>860</COUNTRY_CODE>
        <BILCURRENCY_CODE>860</BILCURRENCY_CODE>
    </record>
    <record>
        <EFFECTIVE_DATE>20231022</EFFECTIVE_DATE>
        <MEMBER_ID>89004000004</MEMBER_ID>
        <LO_RANGE>5614681400000000000</LO_RANGE>
        <HI_RANGE>5614681499999999999</HI_RANGE>
        <BANK_NAME>National Bank for Foreign Economic Affairs</BANK_NAME>
        <PRODUCT_CODE>MCD</PRODUCT_CODE>
        <COUNTRY_CODE>860</COUNTRY_CODE>
        <BILCURRENCY_CODE>860</BILCURRENCY_CODE>
    </record>
    <record>
        <EFFECTIVE_DATE>20231022</EFFECTIVE_DATE>
        <MEMBER_ID>89004000023</MEMBER_ID>
        <LO_RANGE>5614681500000000000</LO_RANGE>
        <HI_RANGE>5614681599999999999</HI_RANGE>
        <BANK_NAME>PJSC "Ravnaq-bank"</BANK_NAME>
        <PRODUCT_CODE>MCD</PRODUCT_CODE>
        <COUNTRY_CODE>860</COUNTRY_CODE>
        <BILCURRENCY_CODE>860</BILCURRENCY_CODE>
    </record>
    <record>
        <EFFECTIVE_DATE>20231022</EFFECTIVE_DATE>
        <MEMBER_ID>89004000007</MEMBER_ID>
        <LO_RANGE>5614681600000000000</LO_RANGE>
        <HI_RANGE>5614681699999999999</HI_RANGE>
        <BANK_NAME>JSCB "Uzpromstroybank"</BANK_NAME>
        <PRODUCT_CODE>MCD</PRODUCT_CODE>
        <COUNTRY_CODE>860</COUNTRY_CODE>
        <BILCURRENCY_CODE>860</BILCURRENCY_CODE>
    </record>
    <record>
        <EFFECTIVE_DATE>20231022</EFFECTIVE_DATE>
        <MEMBER_ID>89004000030</MEMBER_ID>
        <LO_RANGE>5614681700000000000</LO_RANGE>
        <HI_RANGE>5614681799999999999</HI_RANGE>
        <BANK_NAME>JSC "Tenge Bank"</BANK_NAME>
        <PRODUCT_CODE>MCD</PRODUCT_CODE>
        <COUNTRY_CODE>860</COUNTRY_CODE>
        <BILCURRENCY_CODE>860</BILCURRENCY_CODE>
    </record>
    <record>
        <EFFECTIVE_DATE>20231022</EFFECTIVE_DATE>
        <MEMBER_ID>89004000005</MEMBER_ID>
        <LO_RANGE>5614681800000000000</LO_RANGE>
        <HI_RANGE>5614681899999999999</HI_RANGE>
        <BANK_NAME>JSCB "Hamkorbank</BANK_NAME>
        <PRODUCT_CODE>MCD</PRODUCT_CODE>
        <COUNTRY_CODE>860</COUNTRY_CODE>
        <BILCURRENCY_CODE>860</BILCURRENCY_CODE>
    </record>
    <record>
        <EFFECTIVE_DATE>20231022</EFFECTIVE_DATE>
        <MEMBER_ID>89004000004</MEMBER_ID>
        <LO_RANGE>5614681900000000000</LO_RANGE>
        <HI_RANGE>5614681999999999999</HI_RANGE>
        <BANK_NAME>National Bank for Foreign Economic Affairs</BANK_NAME>
        <PRODUCT_CODE>MCD</PRODUCT_CODE>
        <COUNTRY_CODE>860</COUNTRY_CODE>
        <BILCURRENCY_CODE>860</BILCURRENCY_CODE>
    </record>
    <record>
        <EFFECTIVE_DATE>20231022</EFFECTIVE_DATE>
        <MEMBER_ID>89004000002</MEMBER_ID>
        <LO_RANGE>5614682000000000000</LO_RANGE>
        <HI_RANGE>5614682099999999999</HI_RANGE>
        <BANK_NAME>JSC "Xalq Bank"</BANK_NAME>
        <PRODUCT_CODE>MCD</PRODUCT_CODE>
        <COUNTRY_CODE>860</COUNTRY_CODE>
        <BILCURRENCY_CODE>860</BILCURRENCY_CODE>
    </record>
    <record>
        <EFFECTIVE_DATE>20231022</EFFECTIVE_DATE>
        <MEMBER_ID>89004000010</MEMBER_ID>
        <LO_RANGE>5614682100000000000</LO_RANGE>
        <HI_RANGE>5614682199999999999</HI_RANGE>
        <BANK_NAME>JSICB "Ipak Yuli"</BANK_NAME>
        <PRODUCT_CODE>MCD</PRODUCT_CODE>
        <COUNTRY_CODE>860</COUNTRY_CODE>
        <BILCURRENCY_CODE>860</BILCURRENCY_CODE>
    </record>
    <record>
        <EFFECTIVE_DATE>20231022</EFFECTIVE_DATE>
        <MEMBER_ID>89004000015</MEMBER_ID>
        <LO_RANGE>5614682200000000000</LO_RANGE>
        <HI_RANGE>5614682299999999999</HI_RANGE>
        <BANK_NAME>JSCB "Kapitalbank"</BANK_NAME>
        <PRODUCT_CODE>MCD</PRODUCT_CODE>
        <COUNTRY_CODE>643</COUNTRY_CODE>
        <BILCURRENCY_CODE>643</BILCURRENCY_CODE>
    </record>
    <record>
        <EFFECTIVE_DATE>20231022</EFFECTIVE_DATE>
        <MEMBER_ID>89004000023</MEMBER_ID>
        <LO_RANGE>5614682300000000000</LO_RANGE>
        <HI_RANGE>5614682399999999999</HI_RANGE>
        <BANK_NAME>PJSC "Ravnaq-bank"</BANK_NAME>
        <PRODUCT_CODE>MCD</PRODUCT_CODE>
        <COUNTRY_CODE>860</COUNTRY_CODE>
        <BILCURRENCY_CODE>860</BILCURRENCY_CODE>
    </record>
    <record>
        <EFFECTIVE_DATE>20231022</EFFECTIVE_DATE>
        <MEMBER_ID>89004000014</MEMBER_ID>
        <LO_RANGE>5614682400000000000</LO_RANGE>
        <HI_RANGE>5614682499999999999</HI_RANGE>
        <BANK_NAME>PJSC "Trasnbank"</BANK_NAME>
        <PRODUCT_CODE>MCD</PRODUCT_CODE>
        <COUNTRY_CODE>643</COUNTRY_CODE>
        <BILCURRENCY_CODE>643</BILCURRENCY_CODE>
    </record>
    <record>
        <EFFECTIVE_DATE>20231022</EFFECTIVE_DATE>
        <MEMBER_ID>89004000024</MEMBER_ID>
        <LO_RANGE>5614682500000000000</LO_RANGE>
        <HI_RANGE>5614682599999999999</HI_RANGE>
        <BANK_NAME>JSC "KDB Uzbekistan"</BANK_NAME>
        <PRODUCT_CODE>MCD</PRODUCT_CODE>
        <COUNTRY_CODE>860</COUNTRY_CODE>
        <BILCURRENCY_CODE>860</BILCURRENCY_CODE>
    </record>
    <record>
        <EFFECTIVE_DATE>20231022</EFFECTIVE_DATE>
        <MEMBER_ID>89004000018</MEMBER_ID>
        <LO_RANGE>5614682600000000000</LO_RANGE>
        <HI_RANGE>5614682699999999999</HI_RANGE>
        <BANK_NAME>JSCB "Asia Aliance Bank"</BANK_NAME>
        <PRODUCT_CODE>MCD</PRODUCT_CODE>
        <COUNTRY_CODE>860</COUNTRY_CODE>
        <BILCURRENCY_CODE>860</BILCURRENCY_CODE>
    </record>
    <record>
        <EFFECTIVE_DATE>20231022</EFFECTIVE_DATE>
        <MEMBER_ID>89004000006</MEMBER_ID>
        <LO_RANGE>5614682700000000000</LO_RANGE>
        <HI_RANGE>5614682799999999999</HI_RANGE>
        <BANK_NAME>JSCB "Mikrokreditbank"</BANK_NAME>
        <PRODUCT_CODE>MCD</PRODUCT_CODE>
        <COUNTRY_CODE>860</COUNTRY_CODE>
        <BILCURRENCY_CODE>860</BILCURRENCY_CODE>
    </record>
    <record>
        <EFFECTIVE_DATE>20231022</EFFECTIVE_DATE>
        <MEMBER_ID>89004000008</MEMBER_ID>
        <LO_RANGE>5614682800000000000</LO_RANGE>
        <HI_RANGE>5614682899999999999</HI_RANGE>
        <BANK_NAME>JSCB "QishloqQurilishBank"</BANK_NAME>
        <PRODUCT_CODE>MCD</PRODUCT_CODE>
        <COUNTRY_CODE>860</COUNTRY_CODE>
        <BILCURRENCY_CODE>860</BILCURRENCY_CODE>
    </record>
    <record>
        <EFFECTIVE_DATE>20231022</EFFECTIVE_DATE>
        <MEMBER_ID>89004000019</MEMBER_ID>
        <LO_RANGE>5614682900000000000</LO_RANGE>
        <HI_RANGE>5614682999999999999</HI_RANGE>
        <BANK_NAME>PJSC "Orient Finance"</BANK_NAME>
        <PRODUCT_CODE>MCD</PRODUCT_CODE>
        <COUNTRY_CODE>860</COUNTRY_CODE>
        <BILCURRENCY_CODE>860</BILCURRENCY_CODE>
    </record>
    <record>
        <EFFECTIVE_DATE>20231022</EFFECTIVE_DATE>
        <MEMBER_ID>89004000009</MEMBER_ID>
        <LO_RANGE>5614683000000000000</LO_RANGE>
        <HI_RANGE>5614683099999999999</HI_RANGE>
        <BANK_NAME>JSCB " Asaka"</BANK_NAME>
        <PRODUCT_CODE>MCD</PRODUCT_CODE>
        <COUNTRY_CODE>860</COUNTRY_CODE>
        <BILCURRENCY_CODE>860</BILCURRENCY_CODE>
    </record>
    <record>
        <EFFECTIVE_DATE>20231022</EFFECTIVE_DATE>
        <MEMBER_ID>89004000016</MEMBER_ID>
        <LO_RANGE>5614683100000000000</LO_RANGE>
        <HI_RANGE>5614683199999999999</HI_RANGE>
        <BANK_NAME>JSCB "Invest Finance Bank"</BANK_NAME>
        <PRODUCT_CODE>MCD</PRODUCT_CODE>
        <COUNTRY_CODE>860</COUNTRY_CODE>
        <BILCURRENCY_CODE>860</BILCURRENCY_CODE>
    </record>
    <record>
        <EFFECTIVE_DATE>20231022</EFFECTIVE_DATE>
        <MEMBER_ID>89004000025</MEMBER_ID>
        <LO_RANGE>5614683200000000000</LO_RANGE>
        <HI_RANGE>5614683299999999999</HI_RANGE>
        <BANK_NAME>PJSC "Madad Invest Bank"</BANK_NAME>
        <PRODUCT_CODE>MCD</PRODUCT_CODE>
        <COUNTRY_CODE>860</COUNTRY_CODE>
        <BILCURRENCY_CODE>860</BILCURRENCY_CODE>
    </record>
</dataset>